{"nodes": [{"id": "home_raven_documents_github_akm2_0_backend_vendor_google_apiclient_services_src_spanner_delete_php", "label": "Delete.php", "file_type": "code", "source_file": "backend/vendor/google/apiclient-services/src/Spanner/Delete.php", "source_location": "L1"}, {"id": "spanner_delete_delete", "label": "Delete", "file_type": "code", "source_file": "backend/vendor/google/apiclient-services/src/Spanner/Delete.php", "source_location": "L20"}, {"id": "model", "label": "Model", "file_type": "code", "source_file": "", "source_location": ""}, {"id": "spanner_delete_delete_setkeyset", "label": ".setKeySet()", "file_type": "code", "source_file": "backend/vendor/google/apiclient-services/src/Spanner/Delete.php", "source_location": "L32"}, {"id": "keyset", "label": "KeySet", "file_type": "code", "source_file": "", "source_location": ""}, {"id": "spanner_delete_delete_getkeyset", "label": ".getKeySet()", "file_type": "code", "source_file": "backend/vendor/google/apiclient-services/src/Spanner/Delete.php", "source_location": "L39"}, {"id": "spanner_delete_delete_settable", "label": ".setTable()", "file_type": "code", "source_file": "backend/vendor/google/apiclient-services/src/Spanner/Delete.php", "source_location": "L46"}, {"id": "spanner_delete_delete_gettable", "label": ".getTable()", "file_type": "code", "source_file": "backend/vendor/google/apiclient-services/src/Spanner/Delete.php", "source_location": "L53"}], "edges": [{"source": "home_raven_documents_github_akm2_0_backend_vendor_google_apiclient_services_src_spanner_delete_php", "target": "spanner_delete_delete", "relation": "contains", "confidence": "EXTRACTED", "source_file": "backend/vendor/google/apiclient-services/src/Spanner/Delete.php", "source_location": "L20", "weight": 1.0}, {"source": "spanner_delete_delete", "target": "model", "relation": "inherits", "confidence": "EXTRACTED", "source_file": "backend/vendor/google/apiclient-services/src/Spanner/Delete.php", "source_location": "L20", "weight": 1.0}, {"source": "spanner_delete_delete", "target": "spanner_delete_delete_setkeyset", "relation": "method", "confidence": "EXTRACTED", "source_file": "backend/vendor/google/apiclient-services/src/Spanner/Delete.php", "source_location": "L32", "weight": 1.0}, {"source": "spanner_delete_delete_setkeyset", "target": "keyset", "relation": "references", "confidence": "EXTRACTED", "source_file": "backend/vendor/google/apiclient-services/src/Spanner/Delete.php", "source_location": "L32", "weight": 1.0, "context": "parameter_type"}, {"source": "spanner_delete_delete", "target": "spanner_delete_delete_getkeyset", "relation": "method", "confidence": "EXTRACTED", "source_file": "backend/vendor/google/apiclient-services/src/Spanner/Delete.php", "source_location": "L39", "weight": 1.0}, {"source": "spanner_delete_delete", "target": "spanner_delete_delete_settable", "relation": "method", "confidence": "EXTRACTED", "source_file": "backend/vendor/google/apiclient-services/src/Spanner/Delete.php", "source_location": "L46", "weight": 1.0}, {"source": "spanner_delete_delete", "target": "spanner_delete_delete_gettable", "relation": "method", "confidence": "EXTRACTED", "source_file": "backend/vendor/google/apiclient-services/src/Spanner/Delete.php", "source_location": "L53", "weight": 1.0}], "raw_calls": []}