{"nodes": [{"id": "home_raven_documents_github_localcbms_backend_app_models_joborder_php", "label": "JobOrder.php", "file_type": "code", "source_file": "backend/app/Models/JobOrder.php", "source_location": "L1"}, {"id": "models_joborder_joborder", "label": "JobOrder", "file_type": "code", "source_file": "backend/app/Models/JobOrder.php", "source_location": "L7"}, {"id": "model", "label": "Model", "file_type": "code", "source_file": "", "source_location": ""}, {"id": "models_joborder_joborder_application", "label": ".application()", "file_type": "code", "source_file": "backend/app/Models/JobOrder.php", "source_location": "L78"}, {"id": "models_joborder_joborder_items", "label": ".items()", "file_type": "code", "source_file": "backend/app/Models/JobOrder.php", "source_location": "L83"}, {"id": "models_joborder_joborder_lcpnaplocation", "label": ".lcpnapLocation()", "file_type": "code", "source_file": "backend/app/Models/JobOrder.php", "source_location": "L88"}, {"id": "models_joborder_joborder_billingaccount", "label": ".billingAccount()", "file_type": "code", "source_file": "backend/app/Models/JobOrder.php", "source_location": "L93"}], "edges": [{"source": "home_raven_documents_github_localcbms_backend_app_models_joborder_php", "target": "model", "relation": "imports", "context": "import", "confidence": "EXTRACTED", "source_file": "backend/app/Models/JobOrder.php", "source_location": "L5", "weight": 1.0}, {"source": "home_raven_documents_github_localcbms_backend_app_models_joborder_php", "target": "models_joborder_joborder", "relation": "contains", "confidence": "EXTRACTED", "source_file": "backend/app/Models/JobOrder.php", "source_location": "L7", "weight": 1.0}, {"source": "models_joborder_joborder", "target": "model", "relation": "inherits", "confidence": "EXTRACTED", "source_file": "backend/app/Models/JobOrder.php", "source_location": "L7", "weight": 1.0}, {"source": "models_joborder_joborder", "target": "models_joborder_joborder_application", "relation": "method", "confidence": "EXTRACTED", "source_file": "backend/app/Models/JobOrder.php", "source_location": "L78", "weight": 1.0}, {"source": "models_joborder_joborder", "target": "models_joborder_joborder_items", "relation": "method", "confidence": "EXTRACTED", "source_file": "backend/app/Models/JobOrder.php", "source_location": "L83", "weight": 1.0}, {"source": "models_joborder_joborder", "target": "models_joborder_joborder_lcpnaplocation", "relation": "method", "confidence": "EXTRACTED", "source_file": "backend/app/Models/JobOrder.php", "source_location": "L88", "weight": 1.0}, {"source": "models_joborder_joborder", "target": "models_joborder_joborder_billingaccount", "relation": "method", "confidence": "EXTRACTED", "source_file": "backend/app/Models/JobOrder.php", "source_location": "L93", "weight": 1.0}], "raw_calls": [{"caller_nid": "models_joborder_joborder_application", "callee": "belongsTo", "is_member_call": true, "source_file": "/home/raven/Documents/GitHub/localcbms/backend/app/Models/JobOrder.php", "source_location": "L80", "receiver": null}, {"caller_nid": "models_joborder_joborder_items", "callee": "hasMany", "is_member_call": true, "source_file": "/home/raven/Documents/GitHub/localcbms/backend/app/Models/JobOrder.php", "source_location": "L85", "receiver": null}, {"caller_nid": "models_joborder_joborder_lcpnaplocation", "callee": "belongsTo", "is_member_call": true, "source_file": "/home/raven/Documents/GitHub/localcbms/backend/app/Models/JobOrder.php", "source_location": "L90", "receiver": null}, {"caller_nid": "models_joborder_joborder_billingaccount", "callee": "belongsTo", "is_member_call": true, "source_file": "/home/raven/Documents/GitHub/localcbms/backend/app/Models/JobOrder.php", "source_location": "L95", "receiver": null}]}